Products.StandardCacheManagers-5.0-py3.11-nspkg.pth
Products/StandardCacheManagers/AcceleratedHTTPCacheManager.py
Products/StandardCacheManagers/RAMCacheManager.py
Products/StandardCacheManagers/__init__.py
Products/StandardCacheManagers/cache.gif
Products/StandardCacheManagers/configure.zcml
Products/StandardCacheManagers/subscribers.py
Products/StandardCacheManagers/dtml/addAccel.dtml
Products/StandardCacheManagers/dtml/addRCM.dtml
Products/StandardCacheManagers/dtml/propsAccel.dtml
Products/StandardCacheManagers/dtml/propsRCM.dtml
Products/StandardCacheManagers/dtml/statsAccel.dtml
Products/StandardCacheManagers/dtml/statsRCM.dtml
Products/StandardCacheManagers/tests/__init__.py
Products/StandardCacheManagers/tests/test_AcceleratedHTTPCacheManager.py
Products/StandardCacheManagers/tests/test_CacheManagerLocation.py
Products.StandardCacheManagers-5.0.dist-info/LICENSE.txt
Products.StandardCacheManagers-5.0.dist-info/METADATA
Products.StandardCacheManagers-5.0.dist-info/WHEEL
Products.StandardCacheManagers-5.0.dist-info/namespace_packages.txt
Products.StandardCacheManagers-5.0.dist-info/top_level.txt
Products.StandardCacheManagers-5.0.dist-info/RECORD
