Metadata-Version: 2.1
Name: Products.StandardCacheManagers
Version: 5.0
Summary: Cache managers for Zope
Home-page: https://github.com/zopefoundation/Products.StandardCacheManagers
Author: Zope Foundation and Contributors
Author-email: zope-dev@zope.dev
License: ZPL 2.1
Project-URL: Issue Tracker, https://github.com/zopefoundation/Products.StandardCacheManagers/issues
Project-URL: Sources, https://github.com/zopefoundation/Products.StandardCacheManagers
Classifier: Development Status :: 6 - Mature
Classifier: Environment :: Web Environment
Classifier: Framework :: Zope
Classifier: Framework :: Zope :: 5
Classifier: License :: OSI Approved :: Zope Public License
Classifier: Operating System :: OS Independent
Classifier: Programming Language :: Python
Classifier: Programming Language :: Python :: 3
Classifier: Programming Language :: Python :: 3.7
Classifier: Programming Language :: Python :: 3.8
Classifier: Programming Language :: Python :: 3.9
Classifier: Programming Language :: Python :: 3.10
Classifier: Programming Language :: Python :: 3.11
Classifier: Programming Language :: Python :: Implementation :: CPython
Requires-Python: >=3.7
License-File: LICENSE.txt
Requires-Dist: setuptools
Requires-Dist: AccessControl
Requires-Dist: transaction
Requires-Dist: Zope (>5)
Requires-Dist: zope.component
